{"Notes":[{"Paper":137,"Section":0,"Paragraph":0,"TranslatorNote":"","Notes":"","LastDate":"2022-07-27T21:18:14.060","Status":1,"Format":1},{"Paper":137,"Section":0,"Paragraph":1,"TranslatorNote":"","Notes":"","LastDate":"2017-02-23T17:22:32.370","Status":1,"Format":3},{"Paper":137,"Section":1,"Paragraph":0,"TranslatorNote":"","Notes":"","LastDate":"2017-02-23T17:21:04.947","Status":1,"Format":2},{"Paper":137,"Section":1,"Paragraph":1,"TranslatorNote":"","Notes":"","LastDate":"2017-02-24T16:49:37.980","Status":1,"Format":3},{"Paper":137,"Section":1,"Paragraph":2,"TranslatorNote":"","Notes":"","LastDate":"2017-02-24T17:12:36.710","Status":1,"Format":3},{"Paper":137,"Section":1,"Paragraph":3,"TranslatorNote":"","Notes":"","LastDate":"2017-02-25T17:38:24.750","Status":1,"Format":3},{"Paper":137,"Section":1,"Paragraph":4,"TranslatorNote":"","Notes":"","LastDate":"2017-02-25T17:55:14.047","Status":1,"Format":3},{"Paper":137,"Section":1,"Paragraph":5,"TranslatorNote":"","Notes":"","LastDate":"2017-02-27T12:57:41.263","Status":1,"Format":3},{"Paper":137,"Section":1,"Paragraph":6,"TranslatorNote":"","Notes":"","LastDate":"2022-07-30T18:32:24.923","Status":1,"Format":3},{"Paper":137,"Section":1,"Paragraph":7,"TranslatorNote":"","Notes":"","LastDate":"2017-02-27T13:31:20.613","Status":1,"Format":3},{"Paper":137,"Section":1,"Paragraph":8,"TranslatorNote":"","Notes":"","LastDate":"2017-02-27T13:39:23.527","Status":1,"Format":3},{"Paper":137,"Section":2,"Paragraph":0,"TranslatorNote":"","Notes":"","LastDate":"2017-02-27T13:40:36.127","Status":1,"Format":2},{"Paper":137,"Section":2,"Paragraph":1,"TranslatorNote":"","Notes":"","LastDate":"2017-02-27T17:09:15.513","Status":1,"Format":3},{"Paper":137,"Section":2,"Paragraph":2,"TranslatorNote":"","Notes":"","LastDate":"2017-02-28T16:43:55.570","Status":1,"Format":3},{"Paper":137,"Section":2,"Paragraph":3,"TranslatorNote":"","Notes":"","LastDate":"2017-03-01T16:55:51.350","Status":1,"Format":3},{"Paper":137,"Section":2,"Paragraph":4,"TranslatorNote":"","Notes":"","LastDate":"2017-03-01T17:19:23.777","Status":1,"Format":3},{"Paper":137,"Section":2,"Paragraph":5,"TranslatorNote":"","Notes":"","LastDate":"2017-03-01T17:27:01.510","Status":1,"Format":3},{"Paper":137,"Section":2,"Paragraph":6,"TranslatorNote":"","Notes":"","LastDate":"2017-03-03T13:14:09.613","Status":1,"Format":3},{"Paper":137,"Section":2,"Paragraph":7,"TranslatorNote":"","Notes":"","LastDate":"2017-03-03T13:29:51.650","Status":1,"Format":3},{"Paper":137,"Section":2,"Paragraph":8,"TranslatorNote":"","Notes":"","LastDate":"2017-03-03T13:37:14.180","Status":1,"Format":3},{"Paper":137,"Section":2,"Paragraph":9,"TranslatorNote":"","Notes":"","LastDate":"2017-03-03T14:18:18.987","Status":1,"Format":3},{"Paper":137,"Section":3,"Paragraph":0,"TranslatorNote":"","Notes":"","LastDate":"2017-03-03T14:19:37.940","Status":1,"Format":2},{"Paper":137,"Section":3,"Paragraph":1,"TranslatorNote":"","Notes":"","LastDate":"2017-03-07T11:23:58.020","Status":1,"Format":3},{"Paper":137,"Section":3,"Paragraph":2,"TranslatorNote":"","Notes":"","LastDate":"2017-03-07T11:42:01.577","Status":1,"Format":3},{"Paper":137,"Section":3,"Paragraph":3,"TranslatorNote":"","Notes":"","LastDate":"2017-03-07T12:04:47.993","Status":1,"Format":3},{"Paper":137,"Section":3,"Paragraph":4,"TranslatorNote":"","Notes":"","LastDate":"2017-03-07T12:52:45.103","Status":1,"Format":3},{"Paper":137,"Section":3,"Paragraph":5,"TranslatorNote":"","Notes":"","LastDate":"2017-03-07T13:07:50.500","Status":1,"Format":3},{"Paper":137,"Section":3,"Paragraph":6,"TranslatorNote":"","Notes":"","LastDate":"2017-03-07T17:13:43.697","Status":1,"Format":3},{"Paper":137,"Section":3,"Paragraph":7,"TranslatorNote":"","Notes":"","LastDate":"2017-03-07T17:47:10.197","Status":1,"Format":3},{"Paper":137,"Section":4,"Paragraph":0,"TranslatorNote":"","Notes":"","LastDate":"2017-03-08T13:18:00.437","Status":1,"Format":2},{"Paper":137,"Section":4,"Paragraph":1,"TranslatorNote":"","Notes":"","LastDate":"2017-03-08T14:08:01.920","Status":1,"Format":3},{"Paper":137,"Section":4,"Paragraph":2,"TranslatorNote":"","Notes":"","LastDate":"2017-03-08T16:31:34","Status":1,"Format":3},{"Paper":137,"Section":4,"Paragraph":3,"TranslatorNote":"","Notes":"","LastDate":"2017-03-09T16:53:53.997","Status":1,"Format":3},{"Paper":137,"Section":4,"Paragraph":4,"TranslatorNote":"","Notes":"","LastDate":"2017-03-10T12:58:25.047","Status":1,"Format":3},{"Paper":137,"Section":4,"Paragraph":5,"TranslatorNote":"","Notes":"","LastDate":"2017-03-10T16:47:57.950","Status":1,"Format":3},{"Paper":137,"Section":4,"Paragraph":6,"TranslatorNote":"","Notes":"","LastDate":"2017-03-11T12:05:37.503","Status":1,"Format":3},{"Paper":137,"Section":4,"Paragraph":7,"TranslatorNote":"","Notes":"","LastDate":"2017-03-12T14:10:18.450","Status":1,"Format":3},{"Paper":137,"Section":4,"Paragraph":8,"TranslatorNote":"","Notes":"","LastDate":"2017-03-12T15:04:20.223","Status":1,"Format":3},{"Paper":137,"Section":4,"Paragraph":9,"TranslatorNote":"","Notes":"","LastDate":"2017-03-13T18:20:38.747","Status":1,"Format":3},{"Paper":137,"Section":4,"Paragraph":10,"TranslatorNote":"","Notes":"","LastDate":"2017-03-14T14:11:06.323","Status":1,"Format":3},{"Paper":137,"Section":4,"Paragraph":11,"TranslatorNote":"","Notes":"","LastDate":"2017-03-14T14:34:32.690","Status":1,"Format":3},{"Paper":137,"Section":4,"Paragraph":12,"TranslatorNote":"","Notes":"","LastDate":"2017-03-14T18:06:20.610","Status":1,"Format":3},{"Paper":137,"Section":4,"Paragraph":13,"TranslatorNote":"","Notes":"","LastDate":"2017-03-14T18:29:17.043","Status":1,"Format":3},{"Paper":137,"Section":4,"Paragraph":14,"TranslatorNote":"","Notes":"","LastDate":"2017-03-16T17:47:18.650","Status":1,"Format":3},{"Paper":137,"Section":4,"Paragraph":15,"TranslatorNote":"","Notes":"","LastDate":"2017-03-16T18:01:47.493","Status":1,"Format":3},{"Paper":137,"Section":4,"Paragraph":16,"TranslatorNote":"","Notes":"","LastDate":"2017-03-19T12:36:16.863","Status":1,"Format":3},{"Paper":137,"Section":4,"Paragraph":17,"TranslatorNote":"","Notes":"","LastDate":"2017-03-19T12:44:33.410","Status":1,"Format":3},{"Paper":137,"Section":5,"Paragraph":0,"TranslatorNote":"","Notes":"","LastDate":"2017-03-19T12:45:34.677","Status":1,"Format":2},{"Paper":137,"Section":5,"Paragraph":1,"TranslatorNote":"","Notes":"","LastDate":"2017-03-22T15:04:15.290","Status":1,"Format":3},{"Paper":137,"Section":5,"Paragraph":2,"TranslatorNote":"","Notes":"","LastDate":"2017-03-22T18:15:49.220","Status":1,"Format":3},{"Paper":137,"Section":5,"Paragraph":3,"TranslatorNote":"","Notes":"","LastDate":"2017-03-25T18:18:10.070","Status":1,"Format":3},{"Paper":137,"Section":5,"Paragraph":4,"TranslatorNote":"","Notes":"","LastDate":"2017-03-25T18:51:24.927","Status":1,"Format":3},{"Paper":137,"Section":6,"Paragraph":0,"TranslatorNote":"","Notes":"","LastDate":"2017-03-25T18:53:22.397","Status":1,"Format":2},{"Paper":137,"Section":6,"Paragraph":1,"TranslatorNote":"","Notes":"","LastDate":"2017-03-26T15:07:15.010","Status":1,"Format":3},{"Paper":137,"Section":6,"Paragraph":2,"TranslatorNote":"","Notes":"","LastDate":"2017-03-27T12:16:36.643","Status":1,"Format":3},{"Paper":137,"Section":6,"Paragraph":3,"TranslatorNote":"","Notes":"","LastDate":"2017-03-27T12:31:44.580","Status":1,"Format":3},{"Paper":137,"Section":6,"Paragraph":4,"TranslatorNote":"","Notes":"","LastDate":"2017-03-27T12:51:37.990","Status":1,"Format":3},{"Paper":137,"Section":6,"Paragraph":5,"TranslatorNote":"","Notes":"","LastDate":"2017-03-27T14:01:05.150","Status":1,"Format":3},{"Paper":137,"Section":6,"Paragraph":6,"TranslatorNote":"","Notes":"","LastDate":"2017-03-27T14:56:28.697","Status":1,"Format":3},{"Paper":137,"Section":7,"Paragraph":0,"TranslatorNote":"","Notes":"","LastDate":"2017-03-27T14:57:35.500","Status":1,"Format":2},{"Paper":137,"Section":7,"Paragraph":1,"TranslatorNote":"","Notes":"","LastDate":"2017-03-28T14:51:02.730","Status":1,"Format":3},{"Paper":137,"Section":7,"Paragraph":2,"TranslatorNote":"","Notes":"","LastDate":"2017-03-28T15:15:10.680","Status":1,"Format":3},{"Paper":137,"Section":7,"Paragraph":3,"TranslatorNote":"","Notes":"","LastDate":"2017-03-29T18:13:11.647","Status":1,"Format":3},{"Paper":137,"Section":7,"Paragraph":4,"TranslatorNote":"","Notes":"","LastDate":"2017-04-01T04:35:11.147","Status":1,"Format":3},{"Paper":137,"Section":7,"Paragraph":5,"TranslatorNote":"","Notes":"","LastDate":"2017-04-01T18:03:24.907","Status":1,"Format":3},{"Paper":137,"Section":7,"Paragraph":6,"TranslatorNote":"","Notes":"","LastDate":"2017-04-01T18:20:12.377","Status":1,"Format":3},{"Paper":137,"Section":7,"Paragraph":7,"TranslatorNote":"","Notes":"","LastDate":"2017-04-01T18:29:50.777","Status":1,"Format":3},{"Paper":137,"Section":7,"Paragraph":8,"TranslatorNote":"","Notes":"","LastDate":"2017-04-02T13:56:30.167","Status":1,"Format":3},{"Paper":137,"Section":7,"Paragraph":9,"TranslatorNote":"","Notes":"","LastDate":"2017-04-02T14:15:49.180","Status":1,"Format":3},{"Paper":137,"Section":7,"Paragraph":10,"TranslatorNote":"","Notes":"","LastDate":"2017-04-02T14:24:08.533","Status":1,"Format":3},{"Paper":137,"Section":7,"Paragraph":11,"TranslatorNote":"","Notes":"","LastDate":"2017-04-02T14:28:08.347","Status":1,"Format":3},{"Paper":137,"Section":7,"Paragraph":12,"TranslatorNote":"","Notes":"","LastDate":"2017-04-02T14:36:03.313","Status":1,"Format":3},{"Paper":137,"Section":7,"Paragraph":13,"TranslatorNote":"","Notes":"","LastDate":"2017-04-03T07:32:08.600","Status":1,"Format":3},{"Paper":137,"Section":7,"Paragraph":14,"TranslatorNote":"","Notes":"","LastDate":"2017-04-03T07:57:17.123","Status":1,"Format":3},{"Paper":137,"Section":8,"Paragraph":0,"TranslatorNote":"","Notes":"","LastDate":"2017-04-03T07:58:29.710","Status":1,"Format":2},{"Paper":137,"Section":8,"Paragraph":1,"TranslatorNote":"","Notes":"","LastDate":"2017-04-03T08:16:04.783","Status":1,"Format":3},{"Paper":137,"Section":8,"Paragraph":2,"TranslatorNote":"","Notes":"","LastDate":"2017-04-03T11:57:10.030","Status":1,"Format":3},{"Paper":137,"Section":8,"Paragraph":3,"TranslatorNote":"","Notes":"","LastDate":"2017-04-03T12:18:29.040","Status":1,"Format":3},{"Paper":137,"Section":8,"Paragraph":4,"TranslatorNote":"","Notes":"","LastDate":"2017-04-03T14:38:27.550","Status":1,"Format":3},{"Paper":137,"Section":8,"Paragraph":5,"TranslatorNote":"","Notes":"","LastDate":"2017-04-04T07:55:25.987","Status":1,"Format":3},{"Paper":137,"Section":8,"Paragraph":6,"TranslatorNote":"","Notes":"","LastDate":"2017-04-03T14:46:46.293","Status":1,"Format":3},{"Paper":137,"Section":8,"Paragraph":7,"TranslatorNote":"","Notes":"","LastDate":"2017-04-03T15:06:45.917","Status":1,"Format":3},{"Paper":137,"Section":8,"Paragraph":8,"TranslatorNote":"","Notes":"","LastDate":"2017-04-03T15:26:44.473","Status":1,"Format":3},{"Paper":137,"Section":8,"Paragraph":9,"TranslatorNote":"","Notes":"","LastDate":"2017-04-04T08:09:53.323","Status":1,"Format":3},{"Paper":137,"Section":8,"Paragraph":10,"TranslatorNote":"","Notes":"","LastDate":"2017-04-04T08:16:55.813","Status":1,"Format":3},{"Paper":137,"Section":8,"Paragraph":11,"TranslatorNote":"","Notes":"","LastDate":"2017-04-04T15:24:55.740","Status":1,"Format":3},{"Paper":137,"Section":8,"Paragraph":12,"TranslatorNote":"","Notes":"","LastDate":"2017-04-04T17:35:27.210","Status":1,"Format":3},{"Paper":137,"Section":8,"Paragraph":13,"TranslatorNote":"","Notes":"","LastDate":"2017-04-04T18:02:29.910","Status":1,"Format":3},{"Paper":137,"Section":8,"Paragraph":14,"TranslatorNote":"","Notes":"","LastDate":"2017-04-04T18:35:25.413","Status":1,"Format":3},{"Paper":137,"Section":8,"Paragraph":15,"TranslatorNote":"","Notes":"","LastDate":"2017-04-05T07:48:41.210","Status":1,"Format":3},{"Paper":137,"Section":8,"Paragraph":16,"TranslatorNote":"","Notes":"","LastDate":"2017-04-05T08:07:30.763","Status":1,"Format":3},{"Paper":137,"Section":8,"Paragraph":17,"TranslatorNote":"","Notes":"","LastDate":"2017-04-05T10:48:23.397","Status":1,"Format":3},{"Paper":137,"Section":8,"Paragraph":18,"TranslatorNote":"","Notes":"","LastDate":"2017-04-05T11:10:09.163","Status":1,"Format":3}]}