{"Notes":[{"Paper":105,"Section":0,"Paragraph":0,"TranslatorNote":"","Notes":"","LastDate":"2022-07-27T21:18:14.060","Status":1,"Format":1},{"Paper":105,"Section":0,"Paragraph":1,"TranslatorNote":"","Notes":"","LastDate":"2014-10-21T08:09:24.960","Status":1,"Format":3},{"Paper":105,"Section":0,"Paragraph":2,"TranslatorNote":"","Notes":"","LastDate":"2014-10-21T08:21:15.710","Status":1,"Format":3},{"Paper":105,"Section":0,"Paragraph":3,"TranslatorNote":"","Notes":"","LastDate":"2014-10-21T08:43:02.173","Status":1,"Format":3},{"Paper":105,"Section":1,"Paragraph":0,"TranslatorNote":"","Notes":"","LastDate":"2014-10-21T08:44:34.147","Status":1,"Format":2},{"Paper":105,"Section":1,"Paragraph":1,"TranslatorNote":"","Notes":"","LastDate":"2014-10-21T11:38:59.880","Status":1,"Format":3},{"Paper":105,"Section":1,"Paragraph":2,"TranslatorNote":"","Notes":"","LastDate":"2014-10-22T10:49:56.793","Status":1,"Format":3},{"Paper":105,"Section":1,"Paragraph":3,"TranslatorNote":"","Notes":"","LastDate":"2014-10-22T11:42:21.247","Status":1,"Format":3},{"Paper":105,"Section":1,"Paragraph":4,"TranslatorNote":"","Notes":"","LastDate":"2014-10-22T12:39:12.027","Status":1,"Format":3},{"Paper":105,"Section":1,"Paragraph":5,"TranslatorNote":"","Notes":"","LastDate":"2014-10-22T17:06:48.413","Status":1,"Format":3},{"Paper":105,"Section":1,"Paragraph":6,"TranslatorNote":"","Notes":"","LastDate":"2014-10-22T18:49:07.797","Status":1,"Format":3},{"Paper":105,"Section":1,"Paragraph":7,"TranslatorNote":"","Notes":"","LastDate":"2014-10-22T19:03:34.837","Status":1,"Format":3},{"Paper":105,"Section":1,"Paragraph":8,"TranslatorNote":"","Notes":"","LastDate":"2014-10-22T19:58:21.130","Status":1,"Format":3},{"Paper":105,"Section":2,"Paragraph":0,"TranslatorNote":"","Notes":"","LastDate":"2014-10-22T20:05:59.977","Status":1,"Format":2},{"Paper":105,"Section":2,"Paragraph":1,"TranslatorNote":"","Notes":"","LastDate":"2014-10-22T20:22:43.753","Status":1,"Format":3},{"Paper":105,"Section":2,"Paragraph":2,"TranslatorNote":"","Notes":"","LastDate":"2014-10-22T20:42:33.910","Status":1,"Format":3},{"Paper":105,"Section":2,"Paragraph":3,"TranslatorNote":"","Notes":"","LastDate":"2014-10-23T00:02:43.867","Status":1,"Format":3},{"Paper":105,"Section":2,"Paragraph":4,"TranslatorNote":"","Notes":"","LastDate":"2014-10-23T00:15:52.533","Status":1,"Format":3},{"Paper":105,"Section":2,"Paragraph":5,"TranslatorNote":"","Notes":"","LastDate":"2014-10-23T00:21:12.527","Status":1,"Format":4},{"Paper":105,"Section":2,"Paragraph":6,"TranslatorNote":"","Notes":"","LastDate":"2014-10-23T00:25:41.630","Status":1,"Format":4},{"Paper":105,"Section":2,"Paragraph":7,"TranslatorNote":"","Notes":"","LastDate":"2014-10-23T11:53:48.007","Status":1,"Format":4},{"Paper":105,"Section":2,"Paragraph":8,"TranslatorNote":"","Notes":"","LastDate":"2014-10-23T12:04:15.153","Status":1,"Format":4},{"Paper":105,"Section":2,"Paragraph":9,"TranslatorNote":"","Notes":"","LastDate":"2014-10-23T12:34:01.783","Status":1,"Format":4},{"Paper":105,"Section":2,"Paragraph":10,"TranslatorNote":"","Notes":"","LastDate":"2014-10-23T12:46:14.980","Status":1,"Format":4},{"Paper":105,"Section":2,"Paragraph":11,"TranslatorNote":"","Notes":"","LastDate":"2014-10-23T18:37:43.160","Status":1,"Format":4},{"Paper":105,"Section":3,"Paragraph":0,"TranslatorNote":"","Notes":"","LastDate":"2014-10-23T18:52:42.680","Status":1,"Format":2},{"Paper":105,"Section":3,"Paragraph":1,"TranslatorNote":"","Notes":"","LastDate":"2014-10-23T19:14:15.617","Status":1,"Format":3},{"Paper":105,"Section":3,"Paragraph":2,"TranslatorNote":"","Notes":"","LastDate":"2014-10-23T19:27:46.750","Status":1,"Format":4},{"Paper":105,"Section":3,"Paragraph":3,"TranslatorNote":"","Notes":"","LastDate":"2014-10-23T20:16:43.730","Status":1,"Format":4},{"Paper":105,"Section":3,"Paragraph":4,"TranslatorNote":"","Notes":"","LastDate":"2014-10-23T20:49:47.813","Status":1,"Format":4},{"Paper":105,"Section":3,"Paragraph":5,"TranslatorNote":"","Notes":"","LastDate":"2014-10-24T16:22:17.733","Status":1,"Format":4},{"Paper":105,"Section":3,"Paragraph":6,"TranslatorNote":"","Notes":"","LastDate":"2014-10-24T16:41:21.100","Status":1,"Format":4},{"Paper":105,"Section":3,"Paragraph":7,"TranslatorNote":"","Notes":"","LastDate":"2014-10-24T17:10:52.480","Status":1,"Format":4},{"Paper":105,"Section":3,"Paragraph":8,"TranslatorNote":"","Notes":"","LastDate":"2014-10-24T17:14:30.553","Status":1,"Format":4},{"Paper":105,"Section":3,"Paragraph":9,"TranslatorNote":"","Notes":"","LastDate":"2014-10-24T17:24:03.383","Status":1,"Format":3},{"Paper":105,"Section":3,"Paragraph":10,"TranslatorNote":"","Notes":"","LastDate":"2014-10-24T19:50:09.297","Status":1,"Format":3},{"Paper":105,"Section":4,"Paragraph":0,"TranslatorNote":"","Notes":"","LastDate":"2014-10-24T19:52:13.577","Status":1,"Format":2},{"Paper":105,"Section":4,"Paragraph":1,"TranslatorNote":"","Notes":"","LastDate":"2014-10-24T20:09:12.750","Status":1,"Format":3},{"Paper":105,"Section":4,"Paragraph":2,"TranslatorNote":"","Notes":"","LastDate":"2014-10-24T20:23:28.730","Status":1,"Format":3},{"Paper":105,"Section":4,"Paragraph":3,"TranslatorNote":"","Notes":"","LastDate":"2014-10-24T20:34:23.740","Status":1,"Format":3},{"Paper":105,"Section":4,"Paragraph":4,"TranslatorNote":"","Notes":"","LastDate":"2014-10-24T20:44:08.147","Status":1,"Format":4},{"Paper":105,"Section":4,"Paragraph":5,"TranslatorNote":"","Notes":"","LastDate":"2014-10-24T20:45:04.593","Status":1,"Format":4},{"Paper":105,"Section":4,"Paragraph":6,"TranslatorNote":"","Notes":"","LastDate":"2014-10-24T20:45:39.237","Status":1,"Format":4},{"Paper":105,"Section":4,"Paragraph":7,"TranslatorNote":"","Notes":"","LastDate":"2014-10-24T21:02:09.077","Status":1,"Format":3},{"Paper":105,"Section":4,"Paragraph":8,"TranslatorNote":"","Notes":"","LastDate":"2014-10-24T21:09:16.270","Status":1,"Format":3},{"Paper":105,"Section":4,"Paragraph":9,"TranslatorNote":"","Notes":"","LastDate":"2014-10-24T23:06:21.520","Status":1,"Format":3},{"Paper":105,"Section":5,"Paragraph":0,"TranslatorNote":"","Notes":"","LastDate":"2014-10-24T23:08:19.623","Status":1,"Format":2},{"Paper":105,"Section":5,"Paragraph":1,"TranslatorNote":"","Notes":"","LastDate":"2014-10-24T23:13:11.243","Status":1,"Format":3},{"Paper":105,"Section":5,"Paragraph":2,"TranslatorNote":"","Notes":"","LastDate":"2014-10-24T23:25:41.330","Status":1,"Format":3},{"Paper":105,"Section":5,"Paragraph":3,"TranslatorNote":"","Notes":"","LastDate":"2014-10-24T23:43:36.233","Status":1,"Format":3},{"Paper":105,"Section":5,"Paragraph":4,"TranslatorNote":"","Notes":"","LastDate":"2014-10-24T23:59:22.170","Status":1,"Format":3},{"Paper":105,"Section":5,"Paragraph":5,"TranslatorNote":"","Notes":"","LastDate":"2014-10-25T18:00:13.683","Status":1,"Format":3},{"Paper":105,"Section":5,"Paragraph":6,"TranslatorNote":"","Notes":"","LastDate":"2014-10-25T18:09:41.507","Status":1,"Format":3},{"Paper":105,"Section":5,"Paragraph":7,"TranslatorNote":"","Notes":"","LastDate":"2014-10-25T18:12:52.370","Status":1,"Format":4},{"Paper":105,"Section":5,"Paragraph":8,"TranslatorNote":"","Notes":"","LastDate":"2014-10-25T18:15:05.817","Status":1,"Format":4},{"Paper":105,"Section":5,"Paragraph":9,"TranslatorNote":"","Notes":"","LastDate":"2014-10-25T19:19:48.333","Status":1,"Format":3},{"Paper":105,"Section":5,"Paragraph":10,"TranslatorNote":"","Notes":"","LastDate":"2014-10-25T19:28:43.643","Status":1,"Format":3},{"Paper":105,"Section":6,"Paragraph":0,"TranslatorNote":"","Notes":"","LastDate":"2014-10-25T19:31:26.780","Status":1,"Format":2},{"Paper":105,"Section":6,"Paragraph":1,"TranslatorNote":"","Notes":"","LastDate":"2014-10-25T20:10:12.387","Status":1,"Format":3},{"Paper":105,"Section":6,"Paragraph":2,"TranslatorNote":"","Notes":"","LastDate":"2014-10-25T20:32:33.833","Status":1,"Format":4},{"Paper":105,"Section":6,"Paragraph":3,"TranslatorNote":"","Notes":"","LastDate":"2014-10-25T20:39:20.660","Status":1,"Format":4},{"Paper":105,"Section":6,"Paragraph":4,"TranslatorNote":"","Notes":"","LastDate":"2014-10-26T18:46:39.787","Status":1,"Format":4},{"Paper":105,"Section":6,"Paragraph":5,"TranslatorNote":"","Notes":"","LastDate":"2014-10-26T19:29:46.950","Status":1,"Format":4},{"Paper":105,"Section":7,"Paragraph":0,"TranslatorNote":"","Notes":"","LastDate":"2022-07-30T18:32:24.923","Status":1,"Format":2},{"Paper":105,"Section":7,"Paragraph":1,"TranslatorNote":"","Notes":"","LastDate":"2014-10-26T20:57:44.127","Status":1,"Format":3},{"Paper":105,"Section":7,"Paragraph":2,"TranslatorNote":"","Notes":"","LastDate":"2014-10-26T21:21:51.653","Status":1,"Format":3},{"Paper":105,"Section":7,"Paragraph":3,"TranslatorNote":"","Notes":"","LastDate":"2014-10-26T23:48:45.353","Status":1,"Format":3},{"Paper":105,"Section":7,"Paragraph":4,"TranslatorNote":"","Notes":"","LastDate":"2014-10-26T23:49:57.667","Status":1,"Format":3},{"Paper":105,"Section":7,"Paragraph":5,"TranslatorNote":"","Notes":"","LastDate":"2014-10-26T23:52:22.017","Status":1,"Format":4},{"Paper":105,"Section":7,"Paragraph":6,"TranslatorNote":"","Notes":"","LastDate":"2014-10-26T23:51:57.643","Status":1,"Format":4},{"Paper":105,"Section":7,"Paragraph":7,"TranslatorNote":"","Notes":"","LastDate":"2014-10-26T23:53:13.410","Status":1,"Format":4},{"Paper":105,"Section":7,"Paragraph":8,"TranslatorNote":"","Notes":"","LastDate":"2014-10-26T23:53:53.720","Status":1,"Format":4},{"Paper":105,"Section":7,"Paragraph":9,"TranslatorNote":"","Notes":"","LastDate":"2014-10-26T23:54:54.020","Status":1,"Format":4},{"Paper":105,"Section":7,"Paragraph":10,"TranslatorNote":"","Notes":"","LastDate":"2014-10-26T23:55:43.310","Status":1,"Format":4},{"Paper":105,"Section":7,"Paragraph":11,"TranslatorNote":"","Notes":"","LastDate":"2014-10-26T23:56:08.527","Status":1,"Format":4},{"Paper":105,"Section":7,"Paragraph":12,"TranslatorNote":"","Notes":"","LastDate":"2014-10-26T23:56:51.980","Status":1,"Format":4},{"Paper":105,"Section":7,"Paragraph":13,"TranslatorNote":"","Notes":"","LastDate":"2014-10-26T23:58:14.087","Status":1,"Format":4},{"Paper":105,"Section":7,"Paragraph":14,"TranslatorNote":"","Notes":"","LastDate":"2014-10-26T23:58:34.860","Status":1,"Format":4},{"Paper":105,"Section":7,"Paragraph":15,"TranslatorNote":"","Notes":"","LastDate":"2014-10-27T00:03:35.080","Status":1,"Format":3},{"Paper":105,"Section":7,"Paragraph":16,"TranslatorNote":"","Notes":"","LastDate":"2014-10-27T00:08:51.463","Status":1,"Format":3},{"Paper":105,"Section":7,"Paragraph":17,"TranslatorNote":"","Notes":"","LastDate":"2014-10-27T00:12:04.347","Status":1,"Format":3},{"Paper":105,"Section":7,"Paragraph":18,"TranslatorNote":"","Notes":"","LastDate":"2014-10-27T00:46:54.680","Status":1,"Format":3},{"Paper":105,"Section":7,"Paragraph":19,"TranslatorNote":"","Notes":"","LastDate":"2014-10-27T00:47:46.447","Status":1,"Format":3}]}